sendlive/__init__.py
sendlive/__main__.py
sendlive/py.typed
sendlive-0.0.3.dist-info/LICENSE
sendlive-0.0.3.dist-info/METADATA
sendlive-0.0.3.dist-info/WHEEL
sendlive-0.0.3.dist-info/entry_points.txt
sendlive-0.0.3.dist-info/RECORD
