Metadata-Version: 2.1
Name: sendlive
Version: 0.0.3
Summary: sendlive
Home-page: https://github.com/LiamBrenner/sendlive
License: GPL-3.0
Author: Liam Brenner
Author-email: liam.brenner@gmail.com
Requires-Python: >=3.9,<4.0
Classifier: Development Status :: 1 - Planning
Classifier: License :: OSI Approved :: GNU General Public License v3 (GPLv3)
Classifier: Programming Language :: Python :: 3
Classifier: Programming Language :: Python :: 3.9
Classifier: Programming Language :: Python :: 3.10
Classifier: Programming Language :: Python :: 3.11
Classifier: Programming Language :: Python :: 3.12
Provides-Extra: aws
Provides-Extra: gcp
Requires-Dist: boto3 (>=1.34.0) ; extra == "aws"
Requires-Dist: click (>=8.1.7)
Requires-Dist: google-cloud-video-live-stream (>=1.6.0) ; extra == "gcp"
Requires-Dist: urllib3 (>=1.26.18,<2.0)
Project-URL: Changelog, https://github.com/LiamBrenner/sendlive/releases
Project-URL: Documentation, https://sendlive.readthedocs.io
Project-URL: Repository, https://github.com/LiamBrenner/sendlive
